financial_dataset_preprocessor/__init__.py
financial_dataset_preprocessor/alias_functions.py
financial_dataset_preprocessor/dataset_concatenator.py
financial_dataset_preprocessor/preprocess_consts.py
financial_dataset_preprocessor/preprocessor.py
financial_dataset_preprocessor/row_preprocessor.py
financial_dataset_preprocessor/timeseries_basis.py
financial_dataset_preprocessor/universal_applications.py
financial_dataset_preprocessor/bbg_timeseries_preprocessor/__init__.py
financial_dataset_preprocessor/bbg_timeseries_preprocessor/bbg_canonical_timeseries_generator.py
financial_dataset_preprocessor/column_preprocessor_basis/__init__.py
financial_dataset_preprocessor/column_preprocessor_basis/office_system_column_basis.py
financial_dataset_preprocessor/column_preprocessor_basis/office_system_column_consts.py
financial_dataset_preprocessor/general_preprocess_utils/__init__.py
financial_dataset_preprocessor/general_preprocess_utils/alias_functions.py
financial_dataset_preprocessor/general_preprocess_utils/parse_utils.py
financial_dataset_preprocessor/general_preprocess_utils/ticker_utils.py
financial_dataset_preprocessor/general_preprocess_utils/type_utils.py
financial_dataset_preprocessor/general_preprocess_utils/unit_utils.py
financial_dataset_preprocessor/menu2110_preprocessor/__init__.py
financial_dataset_preprocessor/menu2110_preprocessor/menu2110.py
financial_dataset_preprocessor/menu2110_preprocessor/menu2110_applications.py
financial_dataset_preprocessor/menu2110_preprocessor/menu2110_class.py
financial_dataset_preprocessor/menu2110_preprocessor/menu2110_column_preprocessor.py
financial_dataset_preprocessor/menu2110_preprocessor/menu2110_consts.py
financial_dataset_preprocessor/menu2110_preprocessor/menu2110_value_preprocessor.py
financial_dataset_preprocessor/menu2160_preprocessor/__init__.py
financial_dataset_preprocessor/menu2160_preprocessor/menu2160.py
financial_dataset_preprocessor/menu2160_preprocessor/menu2160_column_preprocessor.py
financial_dataset_preprocessor-0.4.5.dist-info/METADATA
financial_dataset_preprocessor-0.4.5.dist-info/WHEEL
financial_dataset_preprocessor-0.4.5.dist-info/top_level.txt
financial_dataset_preprocessor-0.4.5.dist-info/RECORD
