Metadata-Version: 2.4
Name: financial_dataset_preprocessor
Version: 0.4.5
Summary: A package for preprocessing financial datasets, powering the Life Asset Management development team.
Home-page: https://github.com/nailen1/financial_dataset_preprocessor
Author: June Young Park
Author-email: juneyoungpaak@gmail.com
Classifier: Development Status :: 3 - Alpha
Classifier: Intended Audience :: Financial and Insurance Industry
Classifier: License :: Other/Proprietary License
Classifier: Programming Language :: Python :: 3
Classifier: Programming Language :: Python :: 3.11
Requires-Python: >=3.11
Requires-Dist: pandas
Requires-Dist: tqdm
Requires-Dist: string_date_controller>=0.3.0
Requires-Dist: financial_dataset_loader>=0.2.7
Requires-Dist: canonical_transformer>=0.2.4
Requires-Dist: mongodb_controller>=0.2.1
Requires-Dist: aws_s3_controller>=0.7.5
Requires-Dist: universal_timeseries_transformer>=0.3.7
Dynamic: author
Dynamic: author-email
Dynamic: classifier
Dynamic: description
Dynamic: description-content-type
Dynamic: home-page
Dynamic: requires-dist
Dynamic: requires-python
Dynamic: summary
